py_veeqo/__init__.py
py_veeqo/exceptions.py
py_veeqo/models.py
py_veeqo/pyveeqo.py
py_veeqo/types.py
py_veeqo/endpoints/__init__.py
py_veeqo/endpoints/bulk_tagging.py
py_veeqo/endpoints/company.py
py_veeqo/endpoints/customers.py
py_veeqo/endpoints/delivery_methods.py
py_veeqo/endpoints/orders.py
py_veeqo/endpoints/products.py
py_veeqo/endpoints/purchase_orders.py
py_veeqo/endpoints/shipments.py
py_veeqo/endpoints/stock_entries.py
py_veeqo/endpoints/stores.py
py_veeqo/endpoints/suppliers.py
py_veeqo/endpoints/tags.py
py_veeqo/endpoints/warehouses.py
py_veeqo-0.1.0.dist-info/LICENSE.txt
py_veeqo-0.1.0.dist-info/METADATA
py_veeqo-0.1.0.dist-info/WHEEL
py_veeqo-0.1.0.dist-info/top_level.txt
py_veeqo-0.1.0.dist-info/RECORD
