Metadata-Version: 2.1
Name: py_veeqo
Version: 0.1.0
Summary: A python wrapper for the Veeqo API for shipping and inventory management.
Home-page: https://github/com/RobHam99/py_veeqo
Author: Robert J. Hamilton
Author-email: hamiltonrobbie@yahoo.co.uk
License: MIT
Classifier: Development Status :: 3 - Alpha
Classifier: Intended Audience :: Developers
Classifier: Topic :: Software Development :: Libraries
Classifier: License :: OSI Approved :: MIT License
Classifier: Programming Language :: Python :: 3.8
License-File: LICENSE.txt
Requires-Dist: requests
